{"en_backend_auth.md":"32cf05df","en_backend_backend.md":"2f3d4155","en_development_testing.md":"d1c1268b","en_index.md":"43dd15e6","en_development_misc.md":"cb084b6f","en_misc_changelog.md":"c0b9cd18","en_backend_cors.md":"cf71dc8c","en_deployment_hosting.md":"09b06e5a","en_vue-webapp_index.md":"ed78bd50","ru_backend_auth.md":"51834f55","en_backend_api.md":"b846d92a","ru_backend_protocols.md":"aa9a0356","ru_backend_backend.md":"69013f36","en_development_ide.md":"ce13b676","en_misc_glossary.md":"a7a64387","en_backend_protocols.md":"4a46fbdf","en_deployment_docker.md":"51e9b046","en_misc_contribute.md":"379f026d","en_frontend_spa-pwa-ssr-ssg.md":"8e5efdfc","en_frontend_css-ui-libs.md":"39866a0e","en_vue-webapp_getting-started.md":"1af92b12","en_frontend_learning.md":"43e96b8a","ru_book_chapter_1__the_vue_3_framework.md":"e09456d6","ru_book_chapter_11__bonus_chapter_-_ux_patterns.md":"28b9fed1","en_vue-webapp_objectives.md":"cb87c2db","en_vue-webapp_guidelines.md":"322f7110","en_test.md":"6a6e2eff","ru_backend_cors.md":"c11b7f32","ru_book_chapter_10__deploying_your_application.md":"a289899e","en_misc_cheat-sheets.md":"d7e8ff0b","ru_backend_api.md":"35b0a965","en_deployment_github-actions.md":"cc7d34b6","index.md":"ad32297a","en_development_libraries.md":"32597b27","en_development_building.md":"cb8a7b2e","en_deployment_ci-cd.md":"1b449774","en_frontend_about-frameworks.md":"7bbc8155","en_development_assets.md":"fc1d01c1","en_development_stores.md":"58628315","en_frontend_architecture.md":"63414678","ru_book_appendix__migrating_from_vue_2.md":"c27d2a26","ru_development_assets.md":"e3dceee0","ru_book_chapter_9__testing_and_source_control.md":"6c6b2cc9","ru_development_building.md":"d5a78337","ru_deployment_hosting.md":"42b07251","ru_book_not-implemented.md":"b485eac6","ru_deployment_docker.md":"eb6f699d","ru_deployment_github-actions.md":"71067dd7","ru_misc_cheat-sheets.md":"7e853c64","ru_misc_changelog.md":"33e6dba0","ru_development_ide.md":"46cffe23","ru_book_chapter_6__progressive_web_applications.md":"5b2e43d6","ru_deployment_ci-cd.md":"8a749806","ru_book_chapter_5__single-page_applications.md":"d294af66","ru_book_chapter_2__software_design_principles_and_patterns.md":"312aee8e","en_misc_introduction.md":"cfe481c8","ru_book_summary.md":"08290b45","ru_book_index.md":"5ed7ad4a","ru_development_stores.md":"9f603418","ru_development_libraries.md":"58d31dea","ru_development_misc.md":"8560f018","ru_frontend_about-frameworks.md":"8830a954","ru_vue-webapp_options_api.md":"751a33ba","ru_vue-webapp_getting-started.md":"03c62ea5","ru_misc_contribute.md":"ddc57efd","ru_frontend_learning.md":"9759aab5","ru_vue-webapp_options_footer.md":"59b488fd","ru_book_chapter_7__data_flow_management.md":"488b669b","ru_book_chapter_8__multithreading_with_web_workers.md":"f644531e","ru_vue-webapp_options_drawer.md":"418b3fe8","ru_index.md":"ea9673d7","ru_misc_glossary.md":"d31fc7fd","ru_vue-webapp_guidelines.md":"fe0cc15d","ru_misc_introduction.md":"c7a7b57e","ru_vue-webapp_readme.md":"6a693d63","ru_vue-webapp_contribution.md":"0a39b423","ru_vue-webapp_options_ga-gp.md":"79535031","ru_development_testing.md":"2846dfdd","ru_frontend_architecture.md":"03973227","ru_frontend_css-ui-libs.md":"6bddb414","ru_vue-webapp_index.md":"ae2074ed","ru_vue-webapp_objectives.md":"d64e04b1","ru_vue-webapp_options_header.md":"bc15cffb","ru_book_chapter_3__setting_up_a_working_project.md":"848b1e7c","ru_book_chapter_4__user_interface_composition_with_components.md":"003336a2","ru_vue-webapp_options_index.md":"28966c35","ru_vue-webapp_options_baseicon.md":"3e5b1e53","ru_vue-webapp_options_i18n.md":"26dffe47","ru_frontend_spa-pwa-ssr-ssg.md":"837f20fb","ru_vue-webapp_options_layout.md":"c2ab5079"}
